hipcheck_sdk/__init__.py
hipcheck_sdk/chunk.py
hipcheck_sdk/cli.py
hipcheck_sdk/engine.py
hipcheck_sdk/error.py
hipcheck_sdk/options.py
hipcheck_sdk/py.typed
hipcheck_sdk/query.py
hipcheck_sdk/server.py
hipcheck_sdk/gen/__init__.py
hipcheck_sdk/gen/hipcheck_pb2.py
hipcheck_sdk/gen/hipcheck_pb2.pyi
hipcheck_sdk/gen/hipcheck_pb2_grpc.py
hipcheck_sdk/gen/types.py
hipcheck_sdk-0.2.1.dist-info/METADATA
hipcheck_sdk-0.2.1.dist-info/WHEEL
hipcheck_sdk-0.2.1.dist-info/licenses/LICENSE
hipcheck_sdk-0.2.1.dist-info/RECORD
