Metadata-Version: 2.4
Name: hipcheck-sdk
Version: 0.2.1
Summary: An SDK for developing Hipcheck plugins
Project-URL: Homepage, https://hipcheck.mitre.org/
Project-URL: Documentation, https://hipcheck.mitre.org/sdk/python/hipcheck_sdk.html
Project-URL: Repository, https://github.com/mitre/hipcheck.git
Project-URL: Issues, https://github.com/mitre/hipcheck/issues
Author-email: j-lanson <jlanson@mitre.org>
License-Expression: Apache-2.0
License-File: LICENSE
Classifier: Operating System :: OS Independent
Classifier: Programming Language :: Python :: 3
Requires-Python: >=3.10
Requires-Dist: asyncio>=3.4.3
Requires-Dist: coverage>=7.6.12
Requires-Dist: datamodel-code-generator>=0.28.5
Requires-Dist: grpcio-tools>=1.70.0
Requires-Dist: grpcio>=1.70.0
Requires-Dist: logging>=0.4.9.6
Requires-Dist: pydantic>=2.10.6
Requires-Dist: pytest-asyncio>=0.26.0
Requires-Dist: pytest>=8.3.5
Requires-Dist: sphinx>=8.1.3
Requires-Dist: wheel>=0.45.1
